{"nodes": [{"id": "tests_strategic_stress_test_2026_ts", "label": "strategic_stress_test_2026.ts", "file_type": "code", "source_file": "tests\\strategic_stress_test_2026.ts", "source_location": "L1"}, {"id": "strategic_stress_test_2026_runstrategicstresstest", "label": "runStrategicStressTest()", "file_type": "code", "source_file": "tests\\strategic_stress_test_2026.ts", "source_location": "L17"}], "edges": [{"source": "tests_strategic_stress_test_2026_ts", "target": "lib_prisma", "relation": "imports_from", "confidence": "EXTRACTED", "source_file": "tests\\strategic_stress_test_2026.ts", "source_location": "L1", "weight": 1.0}, {"source": "tests_strategic_stress_test_2026_ts", "target": "lib_services_requests_create_request", "relation": "imports_from", "confidence": "EXTRACTED", "source_file": "tests\\strategic_stress_test_2026.ts", "source_location": "L2", "weight": 1.0}, {"source": "tests_strategic_stress_test_2026_ts", "target": "lib_services_bids_create_bid", "relation": "imports_from", "confidence": "EXTRACTED", "source_file": "tests\\strategic_stress_test_2026.ts", "source_location": "L3", "weight": 1.0}, {"source": "tests_strategic_stress_test_2026_ts", "target": "lib_services_ai_score_bid", "relation": "imports_from", "confidence": "EXTRACTED", "source_file": "tests\\strategic_stress_test_2026.ts", "source_location": "L4", "weight": 1.0}, {"source": "tests_strategic_stress_test_2026_ts", "target": "lib_services_offers_accept_offer", "relation": "imports_from", "confidence": "EXTRACTED", "source_file": "tests\\strategic_stress_test_2026.ts", "source_location": "L5", "weight": 1.0}, {"source": "tests_strategic_stress_test_2026_ts", "target": "lib_services_payments_pay_request", "relation": "imports_from", "confidence": "EXTRACTED", "source_file": "tests\\strategic_stress_test_2026.ts", "source_location": "L6", "weight": 1.0}, {"source": "tests_strategic_stress_test_2026_ts", "target": "lib_services_transactions_settle_order", "relation": "imports_from", "confidence": "EXTRACTED", "source_file": "tests\\strategic_stress_test_2026.ts", "source_location": "L7", "weight": 1.0}, {"source": "tests_strategic_stress_test_2026_ts", "target": "lib_services_transactions_deposit_funds", "relation": "imports_from", "confidence": "EXTRACTED", "source_file": "tests\\strategic_stress_test_2026.ts", "source_location": "L8", "weight": 1.0}, {"source": "tests_strategic_stress_test_2026_ts", "target": "config", "relation": "imports_from", "confidence": "EXTRACTED", "source_file": "tests\\strategic_stress_test_2026.ts", "source_location": "L9", "weight": 1.0}, {"source": "tests_strategic_stress_test_2026_ts", "target": "strategic_stress_test_2026_runstrategicstresstest", "relation": "contains", "confidence": "EXTRACTED", "source_file": "tests\\strategic_stress_test_2026.ts", "source_location": "L17", "weight": 1.0}], "raw_calls": [{"caller_nid": "strategic_stress_test_2026_runstrategicstresstest", "callee": "log", "source_file": "tests\\strategic_stress_test_2026.ts", "source_location": "L19"}, {"caller_nid": "strategic_stress_test_2026_runstrategicstresstest", "callee": "now", "source_file": "tests\\strategic_stress_test_2026.ts", "source_location": "L22"}, {"caller_nid": "strategic_stress_test_2026_runstrategicstresstest", "callee": "log", "source_file": "tests\\strategic_stress_test_2026.ts", "source_location": "L25"}, {"caller_nid": "strategic_stress_test_2026_runstrategicstresstest", "callee": "create", "source_file": "tests\\strategic_stress_test_2026.ts", "source_location": "L26"}, {"caller_nid": "strategic_stress_test_2026_runstrategicstresstest", "callee": "now", "source_file": "tests\\strategic_stress_test_2026.ts", "source_location": "L27"}, {"caller_nid": "strategic_stress_test_2026_runstrategicstresstest", "callee": "create", "source_file": "tests\\strategic_stress_test_2026.ts", "source_location": "L29"}, {"caller_nid": "strategic_stress_test_2026_runstrategicstresstest", "callee": "now", "source_file": "tests\\strategic_stress_test_2026.ts", "source_location": "L30"}, {"caller_nid": "strategic_stress_test_2026_runstrategicstresstest", "callee": "create", "source_file": "tests\\strategic_stress_test_2026.ts", "source_location": "L32"}, {"caller_nid": "strategic_stress_test_2026_runstrategicstresstest", "callee": "now", "source_file": "tests\\strategic_stress_test_2026.ts", "source_location": "L33"}, {"caller_nid": "strategic_stress_test_2026_runstrategicstresstest", "callee": "findFirst", "source_file": "tests\\strategic_stress_test_2026.ts", "source_location": "L35"}, {"caller_nid": "strategic_stress_test_2026_runstrategicstresstest", "callee": "log", "source_file": "tests\\strategic_stress_test_2026.ts", "source_location": "L81"}, {"caller_nid": "strategic_stress_test_2026_runstrategicstresstest", "callee": "map", "source_file": "tests\\strategic_stress_test_2026.ts", "source_location": "L88"}, {"caller_nid": "strategic_stress_test_2026_runstrategicstresstest", "callee": "from", "source_file": "tests\\strategic_stress_test_2026.ts", "source_location": "L88"}, {"caller_nid": "strategic_stress_test_2026_runstrategicstresstest", "callee": "all", "source_file": "tests\\strategic_stress_test_2026.ts", "source_location": "L89"}, {"caller_nid": "strategic_stress_test_2026_runstrategicstresstest", "callee": "filter", "source_file": "tests\\strategic_stress_test_2026.ts", "source_location": "L90"}, {"caller_nid": "strategic_stress_test_2026_runstrategicstresstest", "callee": "log", "source_file": "tests\\strategic_stress_test_2026.ts", "source_location": "L91"}, {"caller_nid": "strategic_stress_test_2026_runstrategicstresstest", "callee": "toFixed", "source_file": "tests\\strategic_stress_test_2026.ts", "source_location": "L91"}, {"caller_nid": "strategic_stress_test_2026_runstrategicstresstest", "callee": "now", "source_file": "tests\\strategic_stress_test_2026.ts", "source_location": "L91"}, {"caller_nid": "strategic_stress_test_2026_runstrategicstresstest", "callee": "now", "source_file": "tests\\strategic_stress_test_2026.ts", "source_location": "L94"}, {"caller_nid": "strategic_stress_test_2026_runstrategicstresstest", "callee": "log", "source_file": "tests\\strategic_stress_test_2026.ts", "source_location": "L95"}, {"caller_nid": "strategic_stress_test_2026_runstrategicstresstest", "callee": "log", "source_file": "tests\\strategic_stress_test_2026.ts", "source_location": "L96"}, {"caller_nid": "strategic_stress_test_2026_runstrategicstresstest", "callee": "toFixed", "source_file": "tests\\strategic_stress_test_2026.ts", "source_location": "L96"}, {"caller_nid": "strategic_stress_test_2026_runstrategicstresstest", "callee": "log", "source_file": "tests\\strategic_stress_test_2026.ts", "source_location": "L97"}, {"caller_nid": "strategic_stress_test_2026_runstrategicstresstest", "callee": "toFixed", "source_file": "tests\\strategic_stress_test_2026.ts", "source_location": "L97"}, {"caller_nid": "strategic_stress_test_2026_runstrategicstresstest", "callee": "log", "source_file": "tests\\strategic_stress_test_2026.ts", "source_location": "L98"}, {"caller_nid": "strategic_stress_test_2026_runstrategicstresstest", "callee": "toFixed", "source_file": "tests\\strategic_stress_test_2026.ts", "source_location": "L98"}, {"caller_nid": "strategic_stress_test_2026_runstrategicstresstest", "callee": "log", "source_file": "tests\\strategic_stress_test_2026.ts", "source_location": "L101"}, {"caller_nid": "strategic_stress_test_2026_runstrategicstresstest", "callee": "warn", "source_file": "tests\\strategic_stress_test_2026.ts", "source_location": "L103"}, {"caller_nid": "strategic_stress_test_2026_runstrategicstresstest", "callee": "error", "source_file": "tests\\strategic_stress_test_2026.ts", "source_location": "L107"}, {"caller_nid": "strategic_stress_test_2026_runstrategicstresstest", "callee": "$disconnect", "source_file": "tests\\strategic_stress_test_2026.ts", "source_location": "L109"}]}